api/__init__.py
api/admin.py
api/apps.py
api/models.py
api/tests.py
api/urls.py
api/views.py
api/migrations/__init__.py
feedback/__init__.py
feedback/admin.py
feedback/apps.py
feedback/emails.py
feedback/forms.py
feedback/models.py
feedback/tasks.py
feedback/tests.py
feedback/views.py
feedback/migrations/__init__.py
feedback/templates/contact.html
feedback/templates/feed_base.html
feedback/templates/feedback/email/feedback_email_body.txt
feedback/templates/feedback/email/feedback_email_subject.txt
models/__init__.py
models/admin.py
models/apps.py
models/forms.py
models/models.py
models/tests.py
models/urls.py
models/views.py
models/migrations/0001_initial.py
models/migrations/__init__.py
models/templates/base.html
models/templates/contact.html
models/templates/feed_base.html
models/templates/home.html
models/templates/signup.html
todo_v3/__init__.py
todo_v3/celery.py
todo_v3/settings.py
todo_v3/test_settings.py
todo_v3/urls.py
todo_v3/wsgi.py
todolisthub_v2-1.0.3.data/scripts/todo_manage
users/__init__.py
users/admin.py
users/apps.py
users/forms.py
users/models.py
users/serializers.py
users/tests.py
users/urls.py
users/views.py
users/migrations/0001_initial.py
users/migrations/__init__.py
todolisthub_v2-1.0.3.dist-info/LICENSE
todolisthub_v2-1.0.3.dist-info/METADATA
todolisthub_v2-1.0.3.dist-info/WHEEL
todolisthub_v2-1.0.3.dist-info/top_level.txt
todolisthub_v2-1.0.3.dist-info/RECORD
