Metadata-Version: 2.1
Name: todolisthub-v2
Version: 1.0.3
Summary: A simple Django app to keep track of your todo list. It comes with a RESTful API, celery task queue, Oauth2 and is fully tested.
Home-page: UNKNOWN
Author: Kenneth Mathenge
Author-email: mathenge@example.com
License: UNKNOWN
Platform: UNKNOWN
Classifier: Environment :: Web Environment
Classifier: Framework :: Django
Classifier: Intended Audience :: Developers
Classifier: Operating System :: OS Independent
Classifier: Programming Language :: Python
Classifier: Programming Language :: Python :: 3.6
Classifier: Topic :: Internet :: WWW/HTTP
Classifier: Topic :: Internet :: WWW/HTTP :: Dynamic Content
Requires-Dist: Django (==2.2.3)
Requires-Dist: celery (==3.1.18)
Requires-Dist: django-allauth (==0.39.1)
Requires-Dist: django-rest-framework (==0.1.0)
Requires-Dist: django-environ (==0.4.5)
Requires-Dist: psycopg2 (==2.8.3)
Requires-Dist: gunicorn (==19.9.0)
Requires-Dist: django-rest-auth (==0.9.5)
Requires-Dist: redis (==3.2.1)
Requires-Dist: fabric3 (==1.14.post1)
Requires-Dist: sentry-sdk (==0.10.2)
